rawproxy/__init__.py
rawproxy/app.py
rawproxy/rawproxy.service
rawproxy-0.0.8.dist-info/METADATA
rawproxy-0.0.8.dist-info/WHEEL
rawproxy-0.0.8.dist-info/top_level.txt
rawproxy-0.0.8.dist-info/RECORD
