Metadata-Version: 2.1
Name: rawproxy
Version: 0.0.8
Summary: a githubusercontent proxy tool
Home-page: https://github.com/DevecorSoft/rawproxy
Author: Devecor
Author-email: devecor@outlook.com
License: UNKNOWN
Project-URL: rawproxy, https://github.com/DevecorSoft/rawproxy
Platform: UNKNOWN
Classifier: Programming Language :: Python :: 3
Classifier: License :: OSI Approved :: MIT License
Classifier: Operating System :: OS Independent
Requires-Python: >=3.6
Requires-Dist: flask (>=2.0.2)
Requires-Dist: gunicorn (>=20.1.0)
Requires-Dist: requests (>=2.27.1)
